glitter2/__init__.py
glitter2/glitter2_style.kv
glitter2/main.py
glitter2/run_app.py
glitter2/utils.py
glitter2/analysis/__init__.py
glitter2/analysis/export.py
glitter2/analysis/export_style.kv
glitter2/channel/__init__.py
glitter2/channel/channel_style.kv
glitter2/channel/channel_widgets.py
glitter2/player/__init__.py
glitter2/player/player_style.kv
glitter2/storage/__init__.py
glitter2/storage/data_file.py
glitter2/storage/legacy.py
glitter2/storage/storage_style.kv
glitter2/tests/__init__.py
glitter2/tests/test_data_file.py
glitter2-0.1.0.dist-info/LICENSE
glitter2-0.1.0.dist-info/METADATA
glitter2-0.1.0.dist-info/WHEEL
glitter2-0.1.0.dist-info/entry_points.txt
glitter2-0.1.0.dist-info/top_level.txt
glitter2-0.1.0.dist-info/RECORD
