Metadata-Version: 2.1
Name: glitter2
Version: 0.1.0
Summary: Video scoring for behavioral experiments.
Home-page: https://github.com/matham/glitter2
Author: Matthew Einhorn
Author-email: moiein2000@gmail.com
License: MIT
Project-URL: Bug Reports, https://github.com/matham/glitter2/issues
Project-URL: Source, https://github.com/matham/glitter2
Platform: UNKNOWN
Classifier: Development Status :: 4 - Beta
Classifier: License :: OSI Approved :: MIT License
Classifier: Programming Language :: Python :: 3.7
Classifier: Programming Language :: Python :: 3.8
Requires-Dist: base-kivy-app
Requires-Dist: ffpyplayer
Requires-Dist: kivy
Requires-Dist: nixio (>=1.5.0b4)
Requires-Dist: numpy
Requires-Dist: h5py
Requires-Dist: kivy-garden.graph (>=0.4.0)
Requires-Dist: kivy-garden.tickmarker (>=3.0.0)
Requires-Dist: kivy-garden.painter (~=0.2.1)
Requires-Dist: kivy-garden.collider (~=0.1.1)
Requires-Dist: tables
Requires-Dist: pandas
Requires-Dist: xlsxwriter
Requires-Dist: tree-config
Provides-Extra: dev
Requires-Dist: pytest (>=3.6) ; extra == 'dev'
Requires-Dist: pytest-cov ; extra == 'dev'
Requires-Dist: flake8 ; extra == 'dev'
Requires-Dist: sphinx-rtd-theme ; extra == 'dev'
Requires-Dist: coveralls ; extra == 'dev'
Requires-Dist: trio ; extra == 'dev'
Requires-Dist: pytest-trio ; extra == 'dev'
Requires-Dist: pyinstaller ; extra == 'dev'
